{
    "USD": [
        {
            "date": "2026-02-20 08:01:31",
            "rate": 12169.41
        },
        {
            "date": "2026-02-20 08:03:24",
            "rate": 12169.41
        },
        {
            "date": "2026-02-20 08:06:28",
            "rate": 12169.41
        },
        {
            "date": "2026-02-20 08:14:31",
            "rate": 12169.41
        },
        {
            "date": "2026-02-20 08:14:53",
            "rate": 12169.41
        },
        {
            "date": "2026-02-20 08:15:04",
            "rate": 12169.41
        },
        {
            "date": "2026-02-20 08:15:40",
            "rate": 12169.41
        },
        {
            "date": "2026-02-20 08:17:51",
            "rate": 12169.41
        },
        {
            "date": "2026-02-20 08:19:49",
            "rate": 12169.41
        },
        {
            "date": "2026-02-20 08:20:53",
            "rate": 12169.41
        },
        {
            "date": "2026-02-20 08:24:02",
            "rate": 12169.41
        },
        {
            "date": "2026-02-20 08:25:16",
            "rate": 12169.41
        },
        {
            "date": "2026-02-20 08:28:14",
            "rate": 12169.41
        },
        {
            "date": "2026-02-20 08:29:37",
            "rate": 12169.41
        },
        {
            "date": "2026-02-20 08:42:49",
            "rate": 12169.41
        },
        {
            "date": "2026-02-20 08:46:31",
            "rate": 12169.41
        }
    ],
    "EUR": [
        {
            "date": "2026-02-20 08:01:31",
            "rate": 14359.9
        },
        {
            "date": "2026-02-20 08:03:24",
            "rate": 14359.9
        },
        {
            "date": "2026-02-20 08:06:28",
            "rate": 14359.9
        },
        {
            "date": "2026-02-20 08:14:31",
            "rate": 14359.9
        },
        {
            "date": "2026-02-20 08:14:53",
            "rate": 14359.9
        },
        {
            "date": "2026-02-20 08:15:04",
            "rate": 14359.9
        },
        {
            "date": "2026-02-20 08:15:40",
            "rate": 14359.9
        },
        {
            "date": "2026-02-20 08:17:51",
            "rate": 14359.9
        },
        {
            "date": "2026-02-20 08:19:49",
            "rate": 14359.9
        },
        {
            "date": "2026-02-20 08:20:53",
            "rate": 14359.9
        },
        {
            "date": "2026-02-20 08:24:02",
            "rate": 14359.9
        },
        {
            "date": "2026-02-20 08:25:16",
            "rate": 14359.9
        },
        {
            "date": "2026-02-20 08:28:14",
            "rate": 14359.9
        },
        {
            "date": "2026-02-20 08:29:37",
            "rate": 14359.9
        },
        {
            "date": "2026-02-20 08:42:49",
            "rate": 14359.9
        },
        {
            "date": "2026-02-20 08:46:31",
            "rate": 14359.9
        }
    ]
}